snake_eyes/__init__.py
snake_eyes_parser-0.1.0.dist-info/METADATA
snake_eyes_parser-0.1.0.dist-info/WHEEL
snake_eyes_parser-0.1.0.dist-info/RECORD
