Metadata-Version: 2.1
Name: snake-eyes-parser
Version: 0.1.0
Summary: Python configuration file parser for evolutionary algorithms
License: Wrapper for the Python config parser to read an ini config file and return a dictionary of typed parameters. For documentation of Python configparser and ini use, see https://docs.python.org/3.8/library/configparser.html
Author: Deacon Seals
Requires-Python: >=3.10,<4.0
Classifier: License :: Other/Proprietary License
Classifier: Programming Language :: Python :: 3
Classifier: Programming Language :: Python :: 3.10
Classifier: Programming Language :: Python :: 3.11
